typehandler/__init__.py
typehandler/process.py
typehandler/tests/__init__.py
typehandler/tests/example.py
typehandler/tests/minimum.py
typehandler-0.5.1.dist-info/METADATA
typehandler-0.5.1.dist-info/WHEEL
typehandler-0.5.1.dist-info/top_level.txt
typehandler-0.5.1.dist-info/RECORD
