Metadata-Version: 2.2
Name: typehandler
Version: 0.5.1
Summary: タイピングゲーム用のモジュール
Home-page: https://github.com/prosamo/typehandler
Author: Prosamo
Author-email: prosamo314@gmail.com
Classifier: Programming Language :: Python :: 3
Classifier: License :: OSI Approved :: MIT License
Classifier: Operating System :: OS Independent
Requires-Python: >=3.6
Dynamic: author
Dynamic: author-email
Dynamic: classifier
Dynamic: description
Dynamic: description-content-type
Dynamic: home-page
Dynamic: requires-python
Dynamic: summary
